google/cloud/vectorsearch/__init__.py
google/cloud/vectorsearch/gapic_version.py
google/cloud/vectorsearch/py.typed
google/cloud/vectorsearch_v1beta/__init__.py
google/cloud/vectorsearch_v1beta/gapic_metadata.json
google/cloud/vectorsearch_v1beta/gapic_version.py
google/cloud/vectorsearch_v1beta/py.typed
google/cloud/vectorsearch_v1beta/services/__init__.py
google/cloud/vectorsearch_v1beta/services/data_object_search_service/__init__.py
google/cloud/vectorsearch_v1beta/services/data_object_search_service/async_client.py
google/cloud/vectorsearch_v1beta/services/data_object_search_service/client.py
google/cloud/vectorsearch_v1beta/services/data_object_search_service/pagers.py
google/cloud/vectorsearch_v1beta/services/data_object_search_service/transports/__init__.py
google/cloud/vectorsearch_v1beta/services/data_object_search_service/transports/base.py
google/cloud/vectorsearch_v1beta/services/data_object_search_service/transports/grpc.py
google/cloud/vectorsearch_v1beta/services/data_object_search_service/transports/grpc_asyncio.py
google/cloud/vectorsearch_v1beta/services/data_object_search_service/transports/rest.py
google/cloud/vectorsearch_v1beta/services/data_object_search_service/transports/rest_base.py
google/cloud/vectorsearch_v1beta/services/data_object_service/__init__.py
google/cloud/vectorsearch_v1beta/services/data_object_service/async_client.py
google/cloud/vectorsearch_v1beta/services/data_object_service/client.py
google/cloud/vectorsearch_v1beta/services/data_object_service/transports/__init__.py
google/cloud/vectorsearch_v1beta/services/data_object_service/transports/base.py
google/cloud/vectorsearch_v1beta/services/data_object_service/transports/grpc.py
google/cloud/vectorsearch_v1beta/services/data_object_service/transports/grpc_asyncio.py
google/cloud/vectorsearch_v1beta/services/data_object_service/transports/rest.py
google/cloud/vectorsearch_v1beta/services/data_object_service/transports/rest_base.py
google_cloud_vectorsearch-0.1.0.dist-info/licenses/LICENSE
google_cloud_vectorsearch-0.1.0.dist-info/METADATA
google_cloud_vectorsearch-0.1.0.dist-info/WHEEL
google_cloud_vectorsearch-0.1.0.dist-info/top_level.txt
google_cloud_vectorsearch-0.1.0.dist-info/RECORD
